Metadata-Version: 2.4
Name: llama-index-storage-kvstore-s3
Version: 0.4.1
Summary: llama-index kvstore s3 integration
Author-email: Your Name <you@example.com>
License-Expression: MIT
License-File: LICENSE
Requires-Python: <4.0,>=3.9
Requires-Dist: boto3<2,>=1.34.27
Requires-Dist: llama-index-core<0.15,>=0.13.0
